README.md
setup.py
chinese_gpt/__init__.py
chinese_gpt/cuda_gelu.py
chinese_gpt/gpt_modeling.py
chinese_gpt/version.py
chinese_gpt.egg-info/PKG-INFO
chinese_gpt.egg-info/SOURCES.txt
chinese_gpt.egg-info/dependency_links.txt
chinese_gpt.egg-info/requires.txt
chinese_gpt.egg-info/top_level.txt