Metadata-Version: 2.1
Name: chinese-gpt
Version: 0.1.2
Summary: Chinese Generative Pre-Training Transformer
Home-page: https://github.com/qywu/Chinese-GPT
Author: Qingyang Wu
Author-email: wilwu@ucdavis.edu
License: UNKNOWN
Platform: UNKNOWN
Classifier: Programming Language :: Python :: 3
Classifier: License :: OSI Approved :: MIT License
Classifier: Operating System :: OS Independent
